mcp_common/README.md
mcp_common/__init__.py
mcp_common/exceptions.py
mcp_common/health.py
mcp_common/py.typed
mcp_common/cli/__init__.py
mcp_common/cli/factory.py
mcp_common/cli/health.py
mcp_common/cli/security.py
mcp_common/cli/settings.py
mcp_common/cli/signals.py
mcp_common/config/README.md
mcp_common/config/__init__.py
mcp_common/config/base.py
mcp_common/config/validation_mixin.py
mcp_common/security/README.md
mcp_common/security/__init__.py
mcp_common/security/api_keys.py
mcp_common/security/sanitization.py
mcp_common/server/__init__.py
mcp_common/server/availability.py
mcp_common/server/base.py
mcp_common/server/runtime.py
mcp_common/ui/README.md
mcp_common/ui/__init__.py
mcp_common/ui/panels.py
mcp_common-0.4.8.dist-info/METADATA
mcp_common-0.4.8.dist-info/WHEEL
mcp_common-0.4.8.dist-info/licenses/LICENSE
mcp_common-0.4.8.dist-info/RECORD
