Metadata-Version: 2.4
Name: mcp-common
Version: 0.4.8
Summary: Oneiric-Native foundation library providing battle-tested patterns for MCP (Model Context Protocol) servers, with YAML configuration, Rich UI, and CLI lifecycle management
Project-URL: Homepage, https://github.com/lesleslie/mcp-common
Project-URL: Documentation, https://github.com/lesleslie/mcp-common#readme
Project-URL: Repository, https://github.com/lesleslie/mcp-common
Project-URL: Issues, https://github.com/lesleslie/mcp-common/issues
Author-email: Les Leslie <les@wedgwoodwebworks.com>
License: BSD-3-Clause
License-File: LICENSE
Keywords: configuration,http-client,mcp,model-context-protocol,security,utilities
Classifier: Development Status :: 3 - Alpha
Classifier: Intended Audience :: Developers
Classifier: License :: OSI Approved :: BSD License
Classifier: Programming Language :: Python :: 3
Classifier: Programming Language :: Python :: 3.13
Classifier: Topic :: Internet :: WWW/HTTP :: HTTP Servers
Classifier: Topic :: Software Development :: Libraries :: Python Modules
Classifier: Typing :: Typed
Requires-Python: >=3.13
Requires-Dist: oneiric>=0.3.6
Requires-Dist: psutil>=7.2.1
Requires-Dist: pydantic>=2.12.5
Requires-Dist: pyyaml>=6.0.3
Requires-Dist: rich>=14.2.0
Requires-Dist: typer>=0.21.0
